## Chapter 3. Compiling for the Java Virtual Machine
Java虚拟机是为支持Java编程语言而设计的。Oracle的JDK软件包含从Java编程语言编写的源代码到Java虚拟机指令集的编译器，以及实现Java虚拟机本身的运行时系统。了解编译器是如何利用Java虚拟机的，对于未来的编译器编写者和试图了解Java虚拟机本身的人都很有用。本章的编号章节不规范。

请注意，术语“编译器”有时用于指从Java虚拟机的指令集到特定CPU的指令集的转换器。这种转换器的一个示例是即时(JIT)代码生成器，它仅在加载Java虚拟机代码之后生成特定于平台的指令。本章不讨论与代码生成相关的问题，只讨论与将用Java编程语言编写的源代码编译为Java虚拟机指令相关的问题。
### 3.1. Format of Examples
本章主要包括源代码示例以及Oracle JDK 1.0.2版本中的javac编译器为示例生成的带注释的Java虚拟机代码清单。Java虚拟机代码是用Oracle的javap实用程序输出的非正式“虚拟机汇编语言”编写的，随JDK发布。您可以使用javap生成编译方法的其他示例。

任何读过汇编代码的人都应该熟悉示例的格式。每条指令的形式为:
```
<index> <opcode> [ <operand1> [ <operand2>... ]] [<comment>]
```

<index>是包含该方法的Java虚拟机代码字节的数组中指令的操作码的索引。或者，<index>可以被认为是方法开始处的字节偏移量。<opcode>是指令操作码的助记符，零个或多个<operandN>是指令的操作数。可选的<comment>在行尾注释语法中给出:
```
8   bipush 100     // Push int constant 100
```
注释中的一些内容是由javap发出的;其余部分由作者提供。每条指令前面的<index>可以用作控制转移指令的目标。例如，goto8指令将控制转移到索引为8的指令。注意，Java虚拟机控制传输指令的实际操作数是这些指令的操作码地址的偏移量;这些操作数由javap显示(在本章中展示)，更容易将偏移量读取到它们的方法中。

在表示运行时常数池索引的操作数前面加一个散列符号，然后在指令后面加一个注释，标识所引用的运行时常数池项，如下所示:
```
10  ldc #1         // Push float constant 100.0
or:
9   invokevirtual #4    // Method Example.addTwo(II)I
```
出于本章的目的，我们不担心指定诸如操作数大小之类的细节。

3.2. Use of Constants, Local Variables, and Control Constructs常量、局部变量和控制结构的使用
Java虚拟机代码展示了一组由Java虚拟机的设计和类型使用强加的通用特征。在第一个例子中，我们遇到了许多这样的情况，并对它们进行了一些详细的考虑。

spin方法只是围绕一个空的for循环旋转100次:
``````
void spin() {
    int i;
    for (i = 0; i < 100; i++) {
        ;    // Loop body is empty
    }
}

``````
编译器可以将spin编译为:
``````
0   iconst_0       // Push int constant 0
1   istore_1       // Store into local variable 1 (i=0)
2   goto 8         // First time through don't increment
5   iinc 1 1       // Increment local variable 1 by 1 (i++)
8   iload_1        // Push local variable 1 (i)
9   bipush 100     // Push int constant 100
11  if_icmplt 5    // Compare and loop if less than (i < 100)
14  return         // Return void when done
``````
Java虚拟机是面向堆栈的，大多数操作从Java虚拟机当前帧的操作数堆栈中获取一个或多个操作数，或者将结果压回操作数堆栈。每次调用一个方法时，都会创建一个新的帧，并创建一个新的操作数堆栈和一组局部变量供该方法使用(§2.6)。因此，在计算的任何一个点上，每个控制线程都可能有许多帧和相同数量的操作数堆栈，对应于许多嵌套方法调用。只有当前帧中的操作数堆栈是活动的。

Java虚拟机的指令集通过对其各种数据类型的操作使用不同的字节码来区分操作数类型。方法spin只作用于int类型的值。在编译后的代码中，选择对类型化数据(iconst_0、istore_1、iinc、iload_1、if_icmplt)进行操作的指令都是专门针对int类型的。

spin中的两个常量0和100使用两条不同的指令被压入操作数堆栈。使用iconst_0指令(iconst_<i>指令族中的一个)推送0。使用双push指令推入100，该指令将其推入的值作为直接操作数获取。

Java虚拟机经常利用某些操作数的可能性(在iconst_<i>指令的情况下为int常量-1、0、1、2、3、4和5)，将这些操作数隐式地放在操作码中。因为iconst_0指令知道它要压入一个int 0，所以iconst_0不需要存储操作数来告诉它要压入哪个值，也不需要获取或解码操作数。将push(0)编译为bipush(0)是正确的，但这会使编译后的自旋代码长一个字节。一个简单的虚拟机在每次循环时也会花费额外的时间来获取和解码显式操作数。隐式操作数的使用使编译后的代码更加紧凑和高效。

spin中的int i存储为Java虚拟机本地变量1。因为大多数Java虚拟机指令对从操作数堆栈弹出的值进行操作，而不是直接对局部变量进行操作，所以在为Java虚拟机编译的代码中，在局部变量和操作数堆栈之间传输值的指令很常见。这些操作在指令集中也有特殊的支持。在spin中，使用istore_1和iload_1指令将值从本地变量中传递到本地变量，这两个指令都隐式地操作本地变量1。istore_1指令从操作数堆栈中弹出一个int，并将其存储在局部变量1中。iload_1指令将局部变量1中的值压入操作数堆栈。

局部变量的使用(和重用)是编译器编写者的责任。专门的加载和存储指令应该鼓励编译器编写器尽可能多地重用局部变量。生成的代码更快、更紧凑，并且在框架中使用更少的空间。

对局部变量的某些非常频繁的操作是由Java虚拟机专门处理的。inci指令将局部变量的内容增加一个1字节的带符号值。spin中的inc指令将第一个局部变量(它的第一个操作数)加1(它的第二个操作数)。在实现循环结构时，使用inc指令非常方便。

旋转的for循环主要由以下指令完成:
5   iinc 1 1       // Increment local variable 1 by 1 (i++)
8   iload_1        // Push local variable 1 (i)
9   bipush 100     // Push int constant 100
11  if_icmplt 5    // Compare and loop if less than (i < 100)

bipush指令将值100作为int型压入操作数堆栈，然后if_icmplt指令将该值从操作数堆栈中取出，并将其与i进行比较。如果比较成功(变量i小于100)，则将控制转移到索引5，并开始for循环的下一次迭代。否则，控制传递给if_icmplt后面的指令。

如果spin示例对循环计数器使用了int以外的数据类型，则编译后的代码必须更改以反映不同的数据类型。例如，如果spin示例使用double类型而不是int类型，如下所示:


void dspin() {
    double i;
    for (i = 0.0; i < 100.0; i++) {
        ;    // Loop body is empty
    }
}


编译后的代码为:

Method void dspin()
0   dconst_0       // Push double constant 0.0
1   dstore_1       // Store into local variables 1 and 2
2   goto 9         // First time through don't increment
5   dload_1        // Push local variables 1 and 2 
6   dconst_1       // Push double constant 1.0 
7   dadd           // Add; there is no dinc instruction
8   dstore_1       // Store result in local variables 1 and 2
9   dload_1        // Push local variables 1 and 2 
10  ldc2_w #4      // Push double constant 100.0 
13  dcmpg          // There is no if_dcmplt instruction
14  iflt 5         // Compare and loop if less than (i < 100.0)
17  return         // Return void when done


对类型化数据进行操作的指令现在专门用于double类型。(ldc2_w指令将在本章后面讨论。)

回想一下，双精度值占用两个局部变量，尽管它们只能使用两个局部变量的较小索引访问。对于long类型的值也是如此。再举个例子，

double doubleLocals(double d1, double d2) {
    return d1 + d2;
}


becomes

Method double doubleLocals(double,double)
0   dload_1       // First argument in local variables 1 and 2
1   dload_3       // Second argument in local variables 3 and 4
2   dadd
3   dreturn


注意，用于在doubleLocals中存储双精度值的局部变量对的局部变量永远不能单独操作。

Java虚拟机的操作码大小为1字节，因此编译后的代码非常紧凑。然而，1字节的操作码也意味着Java虚拟机指令集必须保持较小。作为妥协，Java虚拟机并没有为所有数据类型提供相等的支持:它不是完全正交的(表2.11.1-A)。

例如，示例spin的For语句中int类型值的比较可以使用单个if_icmplt指令实现;然而，在Java虚拟机指令集中没有一条指令对double类型的值执行条件分支。因此，dspin必须使用dmpg指令和iflt指令来实现对double类型值的比较。

Java虚拟机为int类型的数据提供了最直接的支持。这部分是由于预期Java虚拟机的操作数栈和局部变量数组的高效实现。它还受到典型程序中int数据频率的影响。其他整型没有那么直接的支持。例如，没有字节、char或简短版本的store、load或add指令。下面是使用短代码编写的spin示例:



void sspin() {
    short i;
    for (i = 0; i < 100; i++) {
        ;    // Loop body is empty
    }
}

它必须为Java虚拟机编译，如下所示，使用操作另一种类型(很可能是int)的指令，根据需要在short值和int值之间进行转换，以确保对短数据的操作结果保持在适当的范围内:


Method void sspin()
0   iconst_0
1   istore_1
2   goto 10
5   iload_1        // The short is treated as though an int
6   iconst_1
7   iadd
8   i2s            // Truncate int to short
9   istore_1
10  iload_1
11  bipush 100
13  if_icmplt 5
16  return

在Java虚拟机中缺乏对字节、char和short类型的直接支持并不是特别痛苦，因为这些类型的值在内部被提升为int (byte和short被符号扩展为int, char被零扩展)。因此，对字节、char和短数据的操作可以使用int指令来完成。唯一的额外开销是将int操作的值截断到有效范围。

在Java虚拟机中，长类型和浮点类型具有中间级别的支持，仅缺乏条件控制传输指令的完整补充。